{
  "schema_version": 1,
  "harness": {
    "id": "wp_site_generator_validation_harness",
    "label": "WP Site Generator validation harness scripts",
    "url": "https://github.com/chubes4/wp-site-generator",
    "git_url": "https://github.com/chubes4/wp-site-generator.git",
    "ref": "main",
    "ref_type": "branch"
  },
  "repositories": {
    "homeboy_extensions": {
      "id": "homeboy_extensions",
      "label": "Homeboy Extensions",
      "url": "https://github.com/Extra-Chill/homeboy-extensions",
      "git_url": "https://github.com/Extra-Chill/homeboy-extensions.git",
      "ref": "main",
      "ref_type": "branch"
    },
    "wp_codebox": {
      "id": "wp_codebox",
      "label": "WP Codebox",
      "url": "https://github.com/Automattic/wp-codebox",
      "git_url": "https://github.com/Automattic/wp-codebox.git",
      "ref": "main",
      "ref_type": "branch"
    },
    "static_site_importer": {
      "id": "static_site_importer",
      "label": "Static Site Importer",
      "url": "https://github.com/chubes4/static-site-importer",
      "git_url": "https://github.com/chubes4/static-site-importer.git",
      "ref": "main",
      "ref_type": "branch",
      "target_folder_name": "static-site-importer"
    },
    "block_format_bridge": {
      "id": "block_format_bridge",
      "label": "Block Format Bridge",
      "url": "https://github.com/chubes4/block-format-bridge",
      "git_url": "https://github.com/chubes4/block-format-bridge.git",
      "ref": "main",
      "ref_type": "branch",
      "target_folder_name": "block-format-bridge"
    },
    "block_artifact_compiler": {
      "id": "block_artifact_compiler",
      "label": "Block Artifact Compiler",
      "url": "https://github.com/chubes4/block-artifact-compiler",
      "git_url": "https://github.com/chubes4/block-artifact-compiler.git",
      "ref": "main",
      "ref_type": "branch",
      "target_folder_name": "block-artifact-compiler"
    },
    "html_to_blocks_converter": {
      "id": "html_to_blocks_converter",
      "label": "HTML to Blocks Converter",
      "url": "https://github.com/chubes4/html-to-blocks-converter",
      "git_url": "https://github.com/chubes4/html-to-blocks-converter.git",
      "ref": "main",
      "ref_type": "branch",
      "target_folder_name": "html-to-blocks-converter"
    }
  }
}
